heraclitus/__init__.py
heraclitus/heraclitus.py
heraclitus/data/__init__.py
heraclitus/data/duckdb_connector.py
heraclitus/data/event_log.py
heraclitus/data/xes_handler.py
heraclitus/discovery/__init__.py
heraclitus/discovery/process_discovery.py
heraclitus/metrics/__init__.py
heraclitus/metrics/time_metrics.py
heraclitus/ml/__init__.py
heraclitus/ml/anomaly_detection.py
heraclitus/ml/feature_engineering.py
heraclitus/ml/prediction.py
heraclitus/statistics/__init__.py
heraclitus/statistics/comparison.py
heraclitus/utils/__init__.py
heraclitus/utils/pm4py_converter.py
heraclitus/visualization/__init__.py
heraclitus/visualization/interactive.py
heraclitus/visualization/pm4py_viz.py
heraclitus/visualization/process_map.py
heraclitus-0.3.0.dist-info/LICENSE
heraclitus-0.3.0.dist-info/METADATA
heraclitus-0.3.0.dist-info/WHEEL
heraclitus-0.3.0.dist-info/top_level.txt
heraclitus-0.3.0.dist-info/RECORD
