Metadata-Version: 2.2
Name: heraclitus
Version: 0.3.0
Summary: Process Mining library aimed at making PM accessible to new users
Author: Heraclitus Contributors
License: MIT
Requires-Python: <3.13,>=3.10
License-File: LICENSE
Requires-Dist: numpy>=1.22.0
Requires-Dist: pandas>=1.4.0
Requires-Dist: matplotlib>=3.5.0
Requires-Dist: scipy>=1.8.0
Requires-Dist: plotly>=5.10.0
Requires-Dist: duckdb>=0.7.0
Provides-Extra: dev
Requires-Dist: pytest>=7.0.0; extra == "dev"
Requires-Dist: pytest-cov>=4.0.0; extra == "dev"
Requires-Dist: flake8>=6.0.0; extra == "dev"
Requires-Dist: mypy>=1.0.0; extra == "dev"
Requires-Dist: black>=23.0.0; extra == "dev"
Provides-Extra: pm4py
Requires-Dist: pm4py>=2.2.0; extra == "pm4py"
Provides-Extra: ml
Requires-Dist: scikit-learn>=1.0.0; extra == "ml"
